Metadata-Version: 2.1
Name: calculator-teh
Version: 1.0.0
Summary: Simple calc functions
Home-page: UNKNOWN
Author: Het Shah
Author-email: hetshah2000@gmail.com
License: UNKNOWN
Platform: UNKNOWN
Requires-Python: >=3.6
License-File: LICENSE.txt
